brain_stl/__init__.py
brain_stl/cli.py
brain_stl/data/ref.png
brain_stl/main.py
brain_stl-0.0.1.dist-info/LICENSE
brain_stl-0.0.1.dist-info/METADATA
brain_stl-0.0.1.dist-info/WHEEL
brain_stl-0.0.1.dist-info/entry_points.txt
brain_stl-0.0.1.dist-info/RECORD
