Metadata-Version: 2.3
Name: brain-stl
Version: 0.0.1
Summary: Turn your brain MRI into a printable 3D model in seconds 🧠➡️🖨️
Home-page: https://github.com/codingfisch/brain_stl
License: MIT
Author: codingfisch
Author-email: l_fisc17@wwu.de
Requires-Python: >=3.9,<4.0
Classifier: Intended Audience :: Science/Research
Classifier: License :: OSI Approved :: MIT License
Classifier: Operating System :: OS Independent
Classifier: Programming Language :: Python :: 3
Classifier: Programming Language :: Python :: 3.9
Classifier: Programming Language :: Python :: 3.10
Classifier: Programming Language :: Python :: 3.11
Classifier: Programming Language :: Python :: 3.12
Classifier: Programming Language :: Python :: 3.13
Requires-Dist: PyMCubes
Requires-Dist: dcm2niix
Requires-Dist: deepmriprep
Requires-Dist: fast_simplification (==0.1.7)
Requires-Dist: niftiview
Requires-Dist: trimesh
Project-URL: Repository, https://github.com/codingfisch/brain_stl
